apex_matrix/__init__.py
apex_matrix/matrix.py
apex_matrix-1.1.1.dist-info/LICENSE
apex_matrix-1.1.1.dist-info/METADATA
apex_matrix-1.1.1.dist-info/WHEEL
apex_matrix-1.1.1.dist-info/top_level.txt
apex_matrix-1.1.1.dist-info/RECORD
