Metadata-Version: 2.1
Name: apex_matrix
Version: 1.1.1
Summary: A simple matrix class that handles basic matrix operations
Author-email: Byron Farrell <byronfarrell22@gmail.com>
Project-URL: Homepage, https://github.com/Byron-Farrell/Matrix
Project-URL: Issues, https://github.com/Byron-Farrell/Matrix/issues
Classifier: Programming Language :: Python :: 3
Classifier: License :: OSI Approved :: MIT License
Classifier: Operating System :: OS Independent
Requires-Python: >=3.8
License-File: LICENSE
